linechart/__init__.py
linechart/_version.py
linechart/base.py
linechart/exceptions.py
linechart/paramscan.py
linechart/perf.py
linechart/shortfall.py
linechart/tearsheet.py
linechart/utils.py
linechart-1.10.0.dist-info/LICENSE.txt
linechart-1.10.0.dist-info/WHEEL
linechart-1.10.0.dist-info/METADATA
linechart-1.10.0.dist-info/RECORD
