Metadata-Version: 2.1
Name: linechart
Version: 1.10.0
Summary: Backtest performance analysis and charting for MoonLine.
License: MIT
Author: Tim Wedde
Author-email: tim.wedde@genzai.dev
Requires-Python: >=3.9,<3.12
Classifier: License :: OSI Approved :: MIT License
Classifier: Programming Language :: Python :: 3
Classifier: Programming Language :: Python :: 3.9
Classifier: Programming Language :: Python :: 3.10
Classifier: Programming Language :: Python :: 3.11
Requires-Dist: arrow (>=1.2.3,<2.0.0)
Requires-Dist: empyrical (>=0.5.5,<0.6.0)
Requires-Dist: matplotlib (>=3.6.2,<4.0.0)
Requires-Dist: pandas (>=1.5.2,<2.0.0)
Requires-Dist: quantrocket-client (>=2.8.0.0,<3.0.0.0)
Requires-Dist: scipy (>=1.9.3,<2.0.0)
Requires-Dist: seaborn (>=0.12.1,<0.13.0)
